spacewidget/__init__.py
spacewidget/index.html
spacewidget/widget.py
spacewidget-0.1.9.dist-info/METADATA
spacewidget-0.1.9.dist-info/WHEEL
spacewidget-0.1.9.dist-info/entry_points.txt
spacewidget-0.1.9.dist-info/top_level.txt
spacewidget-0.1.9.dist-info/RECORD
