Metadata-Version: 2.1
Name: spacewidget
Version: 0.1.9
Summary: UNKNOWN
Home-page: https://github.com/foosinn/spacewidget
Author: foosinn
Author-email: foosinn@f2o.io
License: AGPL 3.0
Platform: UNKNOWN
Requires-Dist: aiohttp
